{"status": 2, "hits": 5, "description": "\u200b\u200b\u200b\u200bPicovico is an online video making platform. But, you can easily download your video for offline access, once it is created.<p><br></p>", "tags": [], "created_at": "2017-05-18T08:07:55Z", "agent_id": 9006088933, "thumbs_up": 0, "updated_at": "2017-05-21T08:14:53Z", "attachments": [], "thumbs_down": 0, "seo_data": {"meta_description": "", "meta_title": "", "meta_keywords": ""}, "description_text": "\u200b\u200b\u200b\u200bPicovico is an online video making platform. But, you can easily download your video for offline access, once it is created.   ", "title": "Can I use this software for offline editing?", "category_id": 9000053774, "type": 1, "id": 9000122281, "folder_id": 9000179603}